Metadata-Version: 1.0
Name: speaklater
Version: 1.2
Summary: implements a lazy string for python useful for use with gettext
Home-page: http://dev.pocoo.org/hg/speaklater-main
Author: Armin Ronacher
Author-email: armin.ronacher@active-4.com
License: UNKNOWN
Platform: UNKNOWN
Classifier: Development Status :: 5 - Production/Stable
Classifier: License :: OSI Approved :: BSD License
Classifier: Topic :: Software Development :: Internationalization
Classifier: Programming Language :: Python
